odoo9_addon_l10n_br_zip-9.0.1.0.0-py2.7-nspkg.pth
odoo_addons/l10n_br_zip/__openerp__.py
odoo_addons/l10n_br_zip/__init__.py
odoo_addons/l10n_br_zip/README.rst
odoo_addons/l10n_br_zip/security/ir.model.access.csv
odoo_addons/l10n_br_zip/models/res_partner.py
odoo_addons/l10n_br_zip/models/l10n_br_zip.py
odoo_addons/l10n_br_zip/models/res_bank.py
odoo_addons/l10n_br_zip/models/__init__.py
odoo_addons/l10n_br_zip/models/res_company.py
odoo_addons/l10n_br_zip/i18n/pt_BR.po
odoo_addons/l10n_br_zip/wizard/__init__.py
odoo_addons/l10n_br_zip/wizard/l10n_br_zip_search_view.xml
odoo_addons/l10n_br_zip/wizard/l10n_br_zip_search.py
odoo_addons/l10n_br_zip/test/zip_demo.yml
odoo_addons/l10n_br_zip/views/l10n_br_zip_view.xml
odoo_addons/l10n_br_zip/views/res_partner_view.xml
odoo_addons/l10n_br_zip/views/res_bank_view.xml
odoo_addons/l10n_br_zip/views/res_company_view.xml
odoo_addons/l10n_br_zip/static/description/icon.png
odoo9_addon_l10n_br_zip-9.0.1.0.0.dist-info/top_level.txt
odoo9_addon_l10n_br_zip-9.0.1.0.0.dist-info/WHEEL
odoo9_addon_l10n_br_zip-9.0.1.0.0.dist-info/RECORD
odoo9_addon_l10n_br_zip-9.0.1.0.0.dist-info/metadata.json
odoo9_addon_l10n_br_zip-9.0.1.0.0.dist-info/DESCRIPTION.rst
odoo9_addon_l10n_br_zip-9.0.1.0.0.dist-info/METADATA
odoo9_addon_l10n_br_zip-9.0.1.0.0.dist-info/namespace_packages.txt
